monopolion_evaluator/__init__.py
monopolion_evaluator/__main__.py
monopolion_evaluator/classifier.py
monopolion_evaluator/cli.py
monopolion_evaluator/util.py
monopolion_evaluator/protobuf/__init__.py
monopolion_evaluator/protobuf/game_outcome_pb2.py
monopolion_evaluator/protobuf/parser.py
monopolion_evaluator-0.2.0.dist-info/AUTHORS.rst
monopolion_evaluator-0.2.0.dist-info/LICENSE
monopolion_evaluator-0.2.0.dist-info/METADATA
monopolion_evaluator-0.2.0.dist-info/WHEEL
monopolion_evaluator-0.2.0.dist-info/entry_points.txt
monopolion_evaluator-0.2.0.dist-info/top_level.txt
monopolion_evaluator-0.2.0.dist-info/RECORD
