Metadata-Version: 2.1
Name: monopolion-evaluator
Version: 0.2.0
Summary: Neural net to predict winning probability in Monopoly
Home-page: https://github.com/miermans/monopolion-evaluator
Author: Matt Miermans
Author-email: m.miermans@gmail.com
License: MIT
Project-URL: Documentation, https://monopolion-evaluator.readthedocs.io/
Project-URL: Changelog, https://monopolion-evaluator.readthedocs.io/en/latest/changelog.html
Project-URL: Issue Tracker, https://github.com/miermans/monopolion-evaluator/issues
Keywords: monopoly,ai,machine learning,neural network,deep learning
Platform: UNKNOWN
Classifier: Development Status :: 2 - Pre-Alpha
Classifier: Intended Audience :: Developers
Classifier: License :: OSI Approved :: MIT License
Classifier: Operating System :: Unix
Classifier: Operating System :: POSIX
Classifier: Operating System :: Microsoft :: Windows
Classifier: Programming Language :: Python
Classifier: Programming Language :: Python :: 3.6
Classifier: Programming Language :: Python :: 3.7
Classifier: Programming Language :: Python :: 3.8
Classifier: Programming Language :: Python :: Implementation :: CPython
Classifier: Topic :: Utilities
Requires-Python: >=3.6, <4
Requires-Dist: tensorflow (==2.2.0)
Requires-Dist: protobuf (>=3.12.0)
Requires-Dist: numpy (<1.19.0,>=1.18.0)
Requires-Dist: pandas (>=1.0.0)
